miku_ai/__init__.py
miku_ai/spider.py
miku_ai-0.1.0.dist-info/LICENSE
miku_ai-0.1.0.dist-info/METADATA
miku_ai-0.1.0.dist-info/WHEEL
miku_ai-0.1.0.dist-info/top_level.txt
miku_ai-0.1.0.dist-info/RECORD
