Metadata-Version: 2.1
Name: miku-ai
Version: 0.1.0
Summary: A project about wechat_article_spider
Home-page: https://github.com/GobinFan/Miku_Spider
Author: Gobin
Author-email: gobinmiku@gmail.com
License: UNKNOWN
Platform: UNKNOWN
Classifier: Programming Language :: Python :: 3
Classifier: License :: OSI Approved :: MIT License
Classifier: Operating System :: OS Independent
Requires-Python: >=3.7
License-File: LICENSE
Requires-Dist: aiohttp
Requires-Dist: bs4
Requires-Dist: fake-useragent
